randmat/randmat.py
jkh011120_randmat-0.1.dist-info/METADATA
jkh011120_randmat-0.1.dist-info/WHEEL
jkh011120_randmat-0.1.dist-info/top_level.txt
jkh011120_randmat-0.1.dist-info/RECORD
